packaging/__init__.py
packaging/bdist_prestoadmin.py
prestoadmin/__init__.py
prestoadmin/_version.py
prestoadmin/catalog.py
prestoadmin/collect.py
prestoadmin/config.py
prestoadmin/configure_cmds.py
prestoadmin/coordinator.py
prestoadmin/deploy.py
prestoadmin/fabric_patches.py
prestoadmin/file.py
prestoadmin/main.py
prestoadmin/mode.py
prestoadmin/node.py
prestoadmin/package.py
prestoadmin/plugin.py
prestoadmin/presto-admin-logging.ini
prestoadmin/presto_conf.py
prestoadmin/prestoclient.py
prestoadmin/server.py
prestoadmin/topology.py
prestoadmin/workers.py
prestoadmin/standalone/__init__.py
prestoadmin/standalone/config.py
prestoadmin/util/__init__.py
prestoadmin/util/all_write_handler.py
prestoadmin/util/application.py
prestoadmin/util/base_config.py
prestoadmin/util/constants.py
prestoadmin/util/exception.py
prestoadmin/util/fabric_application.py
prestoadmin/util/fabricapi.py
prestoadmin/util/filesystem.py
prestoadmin/util/hiddenoptgroup.py
prestoadmin/util/httpscacertconnection.py
prestoadmin/util/local_config_util.py
prestoadmin/util/parser.py
prestoadmin/util/presto_config.py
prestoadmin/util/remote_config_util.py
prestoadmin/util/validators.py
prestoadmin/util/version_util.py
prestoadmin/yarn_slider/__init__.py
prestoadmin/yarn_slider/config.py
prestoadmin/yarn_slider/server.py
prestoadmin/yarn_slider/slider.py
prestoadmin-2.12.dist-info/DESCRIPTION.rst
prestoadmin-2.12.dist-info/METADATA
prestoadmin-2.12.dist-info/RECORD
prestoadmin-2.12.dist-info/WHEEL
prestoadmin-2.12.dist-info/entry_points.txt
prestoadmin-2.12.dist-info/metadata.json
prestoadmin-2.12.dist-info/top_level.txt
util/__init__.py
util/http.py
util/semantic_version.py
