Metadata-Version: 2.0
Name: prestoadmin
Version: 2.12
Summary: Presto-admin installs, configures, and manages Presto installations.
Home-page: https://github.com/prestosql/presto-admin
Author: Presto Team
Author-email: UNKNOWN
License: APLv2
Keywords: prestoadmin
Platform: UNKNOWN
Classifier: Development Status :: 2 - Pre-Alpha
Classifier: Intended Audience :: Developers
Classifier: License :: OSI Approved :: Apache Software License
Classifier: Natural Language :: English
Classifier: Programming Language :: Python :: 2
Classifier: Programming Language :: Python :: 2.6
Classifier: Programming Language :: Python :: 2.7
Requires-Dist: Fabric (==1.10.3)
Requires-Dist: argparse (==1.4)
Requires-Dist: flake8 (==2.5.4)
Requires-Dist: overrides (==0.5)
Requires-Dist: paramiko (==1.16.0)
Requires-Dist: pip (==9.0.2)
Requires-Dist: pycparser (==2.18)
Requires-Dist: pyjks (==0.3.0.1)
Requires-Dist: pyjwt (==1.7.1)
Requires-Dist: requests (==2.7.0)
Requires-Dist: retrying (==1.3.3)
Requires-Dist: setuptools (==20.1.1)
Requires-Dist: wheel (==0.29.0)
